Metadata-Version: 2.1
Name: antler
Version: 0.1.2
Summary: Prompt injection generator
Author: M. Borup-Larsen, C. Christoffersen
License: Apache License
Project-URL: Homepage, https://github.com/martinebl/antler
Classifier: Programming Language :: Python :: 3.11
Classifier: Programming Language :: Python :: 3.12
Classifier: Operating System :: OS Independent
Classifier: License :: OSI Approved :: Apache Software License
Requires-Python: >=3.11
License-File: LICENSE
Requires-Dist: ollama >=0.1.7
Requires-Dist: openai >=1.11.1
Requires-Dist: replicate >=0.24.0
Requires-Dist: tqdm >=4.66.1
Requires-Dist: colorama >=0.4.3
Requires-Dist: python-dotenv >=1.0.1
Requires-Dist: backoff >=2.2.1
Provides-Extra: tests
Requires-Dist: pytest >=8.0.0 ; extra == 'tests'
